setup.py
randomdata/__init__.py
randomdata/datagen.py
randomdata/generators.py
randomdata.egg-info/PKG-INFO
randomdata.egg-info/SOURCES.txt
randomdata.egg-info/dependency_links.txt
randomdata.egg-info/requires.txt
randomdata.egg-info/top_level.txt