Metadata-Version: 1.1
Name: randomdata
Version: 0.1a.dev3
Summary: Random data generator.  Creates CSV data files with generated(random) data.
Home-page: https://bitbucket.org/dulds/randomdata/overview
Author: Rodolfo Duldulao, Jr.
Author-email: rnduldulaojr@gmail.com, rduldulao@chikka.com
License: BSD
Platform: UNKNOWN
Classifier: Development Status :: 2 - Pre-Alpha
Classifier: Environment :: Console
Classifier: Topic :: Utilities
